brain_brew/__init__.py
brain_brew/front_matter.py
brain_brew/main.py
brain_brew/utils.py
brain_brew/build_tasks/__init__.py
brain_brew/build_tasks/crowd_anki/__init__.py
brain_brew/build_tasks/crowd_anki/crowd_anki_generate.py
brain_brew/build_tasks/crowd_anki/headers_from_crowdanki.py
brain_brew/build_tasks/crowd_anki/headers_to_crowd_anki.py
brain_brew/build_tasks/crowd_anki/media_group_from_crowd_anki.py
brain_brew/build_tasks/crowd_anki/media_group_to_crowd_anki.py
brain_brew/build_tasks/crowd_anki/note_model_single_from_crowd_anki.py
brain_brew/build_tasks/crowd_anki/note_models_all_from_crowd_anki.py
brain_brew/build_tasks/crowd_anki/note_models_to_crowd_anki.py
brain_brew/build_tasks/crowd_anki/notes_from_crowd_anki.py
brain_brew/build_tasks/crowd_anki/notes_to_crowd_anki.py
brain_brew/build_tasks/crowd_anki/shared_base_notes.py
brain_brew/build_tasks/csvs/__init__.py
brain_brew/build_tasks/csvs/csvs_generate.py
brain_brew/build_tasks/csvs/generate_guids_in_csvs.py
brain_brew/build_tasks/csvs/notes_from_csvs.py
brain_brew/build_tasks/csvs/shared_base_csvs.py
brain_brew/build_tasks/deck_parts/__init__.py
brain_brew/build_tasks/deck_parts/from_yaml_part.py
brain_brew/build_tasks/deck_parts/headers_from_yaml_part.py
brain_brew/build_tasks/deck_parts/media_group_from_folder.py
brain_brew/build_tasks/deck_parts/note_model_from_html_parts.py
brain_brew/build_tasks/deck_parts/note_model_from_yaml_part.py
brain_brew/build_tasks/deck_parts/save_media_group_to_folder.py
brain_brew/build_tasks/deck_parts/save_note_models_to_folder.py
brain_brew/build_tasks/overrides/__init__.py
brain_brew/build_tasks/overrides/headers_override.py
brain_brew/build_tasks/overrides/notes_override.py
brain_brew/commands/__init__.py
brain_brew/commands/argument_reader.py
brain_brew/commands/init_repo/__init__.py
brain_brew/commands/init_repo/init_repo.py
brain_brew/commands/run_recipe/__init__.py
brain_brew/commands/run_recipe/build_task.py
brain_brew/commands/run_recipe/parts_builder.py
Brain_Brew-0.3.11.dist-info/LICENSE
Brain_Brew-0.3.11.dist-info/METADATA
Brain_Brew-0.3.11.dist-info/WHEEL
Brain_Brew-0.3.11.dist-info/entry_points.txt
Brain_Brew-0.3.11.dist-info/top_level.txt
Brain_Brew-0.3.11.dist-info/RECORD
