Metadata-Version: 2.1
Name: Brain-Brew
Version: 0.3.11
Summary: Automated Anki flashcard creation and extraction to/from Csv 
Home-page: https://github.com/ohare93/brain-brew
Author: Jordan Munch O'Hare
Author-email: brainbrew@jordan.munchohare.com
Classifier: Programming Language :: Python :: 3
Classifier: License :: Public Domain
Classifier: Operating System :: OS Independent
Requires-Python: >=3.7
License-File: LICENSE
Requires-Dist: ruamel.yaml.clib >=0.2.2
Requires-Dist: ruamel.yaml >=0.16.10
Requires-Dist: yamale >=3.0.4
